{
	"cash":	923308380,
	"infinity":	586,
	"upgradeBrickCostLevel":	12,
	"upgradeWidthLevel":	14,
	"upgradeHeightLevel":	4,
	"upgradeGameSpeed":	12,
	"upgradeLossPrevention":	5,
	"upgradeRToReset":	1,
	"upgradeTToPattern":	1,
	"maxBrickCostLevel":	22,
	"saveCurrentPattern":	2,
	"upgradeBought":	[0, 0, 0, 0, 0, 0, 0, 0, 0, 0],
	"backgroundMainSelected":	4,
	"upgradeBackgroundMain":	[1, 1, 1, 1],
	"backgroundShopSelected":	4,
	"upgradeBackgroundShop":	[1, 1, 1, 1],
	"backgroundInfSelected":	4,
	"upgradeBackgroundInf":	[1, 1, 1, 1],
	"bricksColorSelected":	4,
	"upgradeBricksColor":	[1, 1, 1, 1],
	"audioBGSelected":	3,
	"upgradeAudioBG":	[1, 1, 1]
}
